<?xml version="1.0" encoding="UTF-8"?>
<objects serializationModel="Studio.02.01.00">
	<object class="ParameterPreset" id="{e9a30d55-0ec1-4a65-8922-dd470788c3c6}">
		<property name="name">
			<value>PitchLower</value>
		</property>
		<relationship name="folder">
			<destination>{b430773f-0f70-4727-a782-4b2ce8ee7481}</destination>
		</relationship>
		<relationship name="parameter">
			<destination>{4f023a68-699f-4806-94e4-83cb277a4e8c}</destination>
		</relationship>
	</object>
	<object class="GameParameter" id="{4f023a68-699f-4806-94e4-83cb277a4e8c}">
		<property name="initialValue">
			<value>0</value>
		</property>
	</object>
</objects>
